MANIFEST.in
setup.cfg
setup.py
builder/__init__.py
builder/main.py
builder/commands/__init__.py
builder/commands/simple.py
builder/commands/test.py
builder/commands/update.py
builder/converter/__init__.py
builder/converter/column_mapping.py
builder/converter/converter.py
builder/converter/converter_mapping.py
builder/converter/list_view.py
builder/converter/nested_view.py
builder/converter/pipeline_view.py
builder/converter/views.py
builder/converter/templates/__init__.py
builder/converter/templates/list_view_template.xml
builder/converter/templates/nested_view_template.xml
builder/converter/templates/pipeline_view_template.xml
builder/uploader/__init__.py
builder/uploader/jenkins_upload.py
jenkins_view_builder.egg-info/PKG-INFO
jenkins_view_builder.egg-info/SOURCES.txt
jenkins_view_builder.egg-info/dependency_links.txt
jenkins_view_builder.egg-info/entry_points.txt
jenkins_view_builder.egg-info/not-zip-safe
jenkins_view_builder.egg-info/requires.txt
jenkins_view_builder.egg-info/top_level.txt
tests/__init__.py
tests/test_converter.py
tests/test_list_view.py
tests/test_nested_view.py
tests/test_pipeline_view.py
tests/test_views.py