Metadata-Version: 1.1
Name: jenkins-view-builder
Version: 0.5.0
Summary: Build jenkins views in YAML
Home-page: https://github.com/piyush0101/jenkins-view-builder
Author: Piyush Srivastava
Author-email: piyush.0101@gmail.com
License: UNKNOWN
Download-URL: https://github.com/piyush0101/jenkins-view-builder/archive/0.5.0.tar.gz
Platform: Any
